deep_toon/__init__.py
deep_toon/decoder.py
deep_toon/encoder.py
deep_toon-0.1.0.dist-info/licenses/LICENSE
deep_toon-0.1.0.dist-info/METADATA
deep_toon-0.1.0.dist-info/WHEEL
deep_toon-0.1.0.dist-info/top_level.txt
deep_toon-0.1.0.dist-info/RECORD
