Metadata-Version: 2.4
Name: deep-toon
Version: 0.1.0
Summary: Deep Token-Oriented Object Notation - Efficient JSON compression for LLM applications
Author: Deep-TOON Contributors
Maintainer: Deep-TOON Contributors
License: Apache-2.0
Project-URL: Homepage, https://github.com/csabakecskemeti/deep-toon-python
Project-URL: Repository, https://github.com/csabakecskemeti/deep-toon-python
Project-URL: Documentation, https://github.com/csabakecskemeti/deep-toon-python#readme
Keywords: json,compression,llm,ai,tokens,optimization,serialization
Classifier: Development Status :: 4 - Beta
Classifier: Intended Audience :: Developers
Classifier: Intended Audience :: Science/Research
Classifier: Operating System :: OS Independent
Classifier: Programming Language :: Python :: 3
Classifier: Programming Language :: Python :: 3.8
Classifier: Programming Language :: Python :: 3.9
Classifier: Programming Language :: Python :: 3.10
Classifier: Programming Language :: Python :: 3.11
Classifier: Programming Language :: Python :: 3.12
Classifier: Topic :: Scientific/Engineering :: Artificial Intelligence
Classifier: Topic :: Software Development :: Libraries :: Python Modules
Classifier: Topic :: Text Processing :: Markup
Classifier: Topic :: Utilities
Requires-Python: >=3.8
License-File: LICENSE
Provides-Extra: dev
Requires-Dist: pytest>=7.0.0; extra == "dev"
Dynamic: license-file
